{
  "index_id": "gsci",
  "data_status": "needs_data",
  "render_status": "blocked_until_ready",
  "review_status": "pending",
  "missing_items": [
    "official_index_page",
    "official_methodology",
    "sector_weights",
    "top_holdings",
    "historical_price_series",
    "historical_returns",
    "max_drawdown",
    "source_date",
    "contract_or_index_method",
    "roll_or_weighting_rules"
  ],
  "basic_info": {
    "index_name_cn": "标普高盛商品指数",
    "index_name_en": "S&P GSCI",
    "index_code": "GSCI",
    "provider": "S&P Dow Jones Indices",
    "region": "全球",
    "market": "Global",
    "currency": "multi_currency",
    "index_type": "commodity",
    "template_type": "commodity",
    "style_theme": "commodity",
    "catalog_focus": "能源、金属、农产品等商品",
    "catalog_asset_class": "商品宽基",
    "identity_status": "catalog_candidate"
  },
  "methodology_summary": {
    "status": "needs_official_methodology",
    "draft_from_catalog": "目录描述显示，该指数关注：能源、金属、农产品等商品。",
    "must_confirm": [
      "样本空间",
      "选样规则",
      "加权方式",
      "调样频率",
      "成分限制"
    ]
  },
  "sector_weights": {
    "status": "missing",
    "items": [],
    "required_for_video": "02_holdings_breakdown"
  },
  "top_holdings": {
    "status": "missing",
    "items": [],
    "required_for_video": "02_holdings_breakdown"
  },
  "valuation_metrics": {
    "status": "missing",
    "expected_by_type": [
      "商品篮子权重",
      "展期规则",
      "历史波动",
      "供需敏感项"
    ],
    "required_for_video": "05_valuation_view"
  },
  "historical_returns": {
    "status": "missing",
    "items": [],
    "required_for_video": "04_return_drawdown_risk"
  },
  "drawdown_stats": {
    "status": "missing",
    "items": [],
    "required_for_video": "04_return_drawdown_risk",
    "calculation_required": "使用公开历史点位计算最大回撤、回撤区间和恢复情况。"
  },
  "dividend_metrics": {
    "status": "not_required",
    "items": [],
    "required_for_video": "05_valuation_view"
  },
  "risk_points": {
    "status": "catalog_draft_needs_review",
    "items": [
      "商品波动高",
      "受供需和地缘因素影响"
    ]
  },
  "role_in_portfolio": {
    "status": "catalog_draft_needs_review",
    "summary": "通胀和商品周期暴露",
    "must_confirm": [
      "核心/卫星定位",
      "适合搭配对象",
      "不适合承担的角色",
      "主要回撤来源"
    ]
  },
  "source_items": [
    {
      "source_id": "global_index_catalog_500",
      "source_type": "catalog",
      "path": "data/global_index_catalog_500.csv",
      "fields_used": [
        "code",
        "name",
        "region",
        "provider",
        "asset_class",
        "focus",
        "role",
        "risks",
        "theme"
      ],
      "allowed_for_final_numbers": false
    }
  ],
  "data_date": {
    "catalog_data": "not_dated",
    "production_data": "not_collected"
  },
  "calculation_notes": [
    "当前 profile 是生产计划资料，不是成片数据文件。",
    "缺口补齐前不得生成成品视频。",
    "未来 data_used.json 必须记录每个数字的来源、字段、区间和计算方法。"
  ]
}